[{"id":"16a99bc9.937dd4","type":"tab","label":"Sonoff","disabled":false,"info":""},{"id":"8b6efa11.bcdc48","type":"tab","label":"Hue & Velbus","disabled":false,"info":""},{"id":"7621567e.e89568","type":"tab","label":"Dashboard","disabled":false,"info":""},{"id":"58ffe4aa.948ebc","type":"tab","label":"Nora","disabled":false,"info":""},{"id":"90d7900f.39219","type":"tab","label":"Google Home","disabled":true,"info":""},{"id":"cac76e2e.508a7","type":"hue-bridge","z":"","name":"Philips Hue","bridge":"192.168.0.170","key":"Z7EXnrr32-2C2ESmIM2VvYt1UpsIg4nSgo77fwTt","interval":"1500"},{"id":"6fb1e1d1.68362","type":"mqtt-broker","z":"","name":"","broker":"192.168.0.142","port":"1883","clientid":"Mosquitto","usetls":false,"compatmode":true,"keepalive":"60","cleansession":true,"birthTopic":"","birthQos":"0","birthPayload":"","closeTopic":"","closeQos":"0","closePayload":"","willTopic":"","willQos":"0","willPayload":""},{"id":"a551ea00.a91cc8","type":"ui_tab","z":"","name":"Lights","icon":"dashboard"},{"id":"bc7372ed.69c55","type":"ui_group","z":"","name":"Home","tab":"a551ea00.a91cc8","disp":true,"width":"6","collapse":false},{"id":"e4d585fc.094dc8","type":"ui_base","theme":{"name":"theme-light","lightTheme":{"default":"#0094CE","baseColor":"#0094CE","baseFont":"-apple-system,BlinkMacSystemFont,Segoe UI,Roboto,Oxygen-Sans,Ubuntu,Cantarell,Helvetica Neue,sans-serif","edited":true,"reset":false},"darkTheme":{"default":"#097479","baseColor":"#097479","baseFont":"-apple-system,BlinkMacSystemFont,Segoe UI,Roboto,Oxygen-Sans,Ubuntu,Cantarell,Helvetica Neue,sans-serif","edited":false},"customTheme":{"name":"Untitled Theme 1","default":"#4B7930","baseColor":"#4B7930","baseFont":"-apple-system,BlinkMacSystemFont,Segoe UI,Roboto,Oxygen-Sans,Ubuntu,Cantarell,Helvetica Neue,sans-serif"},"themeState":{"base-color":{"default":"#0094CE","value":"#0094CE","edited":false},"page-titlebar-backgroundColor":{"value":"#0094CE","edited":false},"page-backgroundColor":{"value":"#fafafa","edited":false},"page-sidebar-backgroundColor":{"value":"#ffffff","edited":false},"group-textColor":{"value":"#1bbfff","edited":false},"group-borderColor":{"value":"#ffffff","edited":false},"group-backgroundColor":{"value":"#ffffff","edited":false},"widget-textColor":{"value":"#111111","edited":false},"widget-backgroundColor":{"value":"#0094ce","edited":false},"widget-borderColor":{"value":"#ffffff","edited":false},"base-font":{"value":"-apple-system,BlinkMacSystemFont,Segoe UI,Roboto,Oxygen-Sans,Ubuntu,Cantarell,Helvetica Neue,sans-serif"}},"angularTheme":{"primary":"indigo","accents":"blue","warn":"red","background":"grey"}},"site":{"name":"Node-RED Dashboard","hideToolbar":"false","allowSwipe":"false","lockMenu":"false","allowTempTheme":"true","dateFormat":"DD/MM/YYYY","sizes":{"sx":48,"sy":48,"gx":6,"gy":6,"cx":6,"cy":6,"px":0,"py":0}}},{"id":"cd4ef92c.02f5a8","type":"nora-config","z":"","name":"nora config","group":"","notify":false},{"id":"88bb4f42.b7938","type":"position-config","z":"","name":"","isValide":"true","longitude":"0","latitude":"0","angleType":"deg","timezoneOffset":"1"},{"id":"5a175440.6b69bc","type":"hue-bridge-node","z":"8b6efa11.bcdc48","name":"","bridge":"cac76e2e.508a7","autoupdates":true,"x":90,"y":20,"wires":[[]]},{"id":"d9f87016.ce0be","type":"ui_switch","z":"7621567e.e89568","name":"","label":"Sonoff 1","group":"bc7372ed.69c55","order":0,"width":0,"height":0,"passthru":false,"decouple":"false","topic":"","style":"","onvalue":"1","onvalueType":"str","onicon":"","oncolor":"","offvalue":"0","offvalueType":"str","officon":"","offcolor":"","x":380,"y":80,"wires":[["edc41408.bbc358","d1986752.9bcb08"]]},{"id":"3068d367.df043c","type":"mqtt in","z":"7621567e.e89568","name":"","topic":"/sonoff1/relay/0","qos":"2","broker":"6fb1e1d1.68362","x":100,"y":80,"wires":[["d9f87016.ce0be","956afe91.f7432"]]},{"id":"edc41408.bbc358","type":"mqtt out","z":"7621567e.e89568","name":"","topic":"/sonoff1/relay/0/set","qos":"2","retain":"","broker":"6fb1e1d1.68362","x":680,"y":80,"wires":[]},{"id":"956afe91.f7432","type":"debug","z":"7621567e.e89568","name":"","active":false,"tosidebar":true,"console":false,"tostatus":false,"complete":"payload","x":390,"y":160,"wires":[]},{"id":"d1986752.9bcb08","type":"debug","z":"7621567e.e89568","name":"","active":false,"tosidebar":true,"console":false,"tostatus":false,"complete":"payload","x":660,"y":160,"wires":[]},{"id":"78c03278.ec53ac","type":"inject","z":"16a99bc9.937dd4","name":"Off @0:15","topic":"","payload":"0","payloadType":"num","repeat":"","crontab":"15 00 * * *","once":false,"onceDelay":0.1,"x":130,"y":40,"wires":[["89d2ff26.c1605"]]},{"id":"62375997.7c78b8","type":"inject","z":"16a99bc9.937dd4","name":"On @ 6:45","topic":"","payload":"1","payloadType":"num","repeat":"","crontab":"45 06 * * *","once":false,"onceDelay":0.1,"x":130,"y":80,"wires":[["89d2ff26.c1605"]]},{"id":"89d2ff26.c1605","type":"mqtt out","z":"16a99bc9.937dd4","name":"TV Kast","topic":"/sonoff1/relay/0/set","qos":"","retain":"","broker":"6fb1e1d1.68362","x":840,"y":60,"wires":[]},{"id":"7a009524.508bec","type":"inject","z":"16a99bc9.937dd4","name":"Toggle","topic":"","payload":"2","payloadType":"num","repeat":"","crontab":"","once":false,"onceDelay":0.1,"x":110,"y":120,"wires":[["89d2ff26.c1605"]]},{"id":"ede0e23c.7802b","type":"function","z":"8b6efa11.bcdc48","name":"set","func":"global.set(\"DiningLight\", msg.payload.on)\nreturn msg;","outputs":1,"noerr":0,"x":750,"y":140,"wires":[[]]},{"id":"81b2a22d.238b5","type":"hue-group","z":"8b6efa11.bcdc48","name":"Kitchen","bridge":"cac76e2e.508a7","groupid":"2","colornamer":true,"x":420,"y":220,"wires":[[]]},{"id":"ebbc0b0f.f13e18","type":"hue-group","z":"8b6efa11.bcdc48","name":"Dining Room","bridge":"cac76e2e.508a7","groupid":"1","colornamer":true,"x":430,"y":280,"wires":[[]]},{"id":"f995b927.3cb4b8","type":"hue-light","z":"8b6efa11.bcdc48","name":"Dining Room Pendant","bridge":"cac76e2e.508a7","lightid":"2","colornamer":false,"x":540,"y":140,"wires":[["ede0e23c.7802b"]]},{"id":"5cea949e.29749c","type":"change","z":"8b6efa11.bcdc48","name":"turn off","rules":[{"t":"set","p":"payload","pt":"msg","to":"false","tot":"bool"}],"action":"","property":"","from":"","to":"","reg":false,"x":260,"y":280,"wires":[["81b2a22d.238b5","ebbc0b0f.f13e18","893c16b0.67f1c8"]]},{"id":"7007e3ab.81318c","type":"velbus-switch","z":"8b6efa11.bcdc48","address":"18","channel":"2","name":"Tafel @trap","x":190,"y":140,"wires":[["99a4866.0b8e078"]]},{"id":"93ef797e.7040c8","type":"velbus-switch","z":"8b6efa11.bcdc48","address":"18","channel":"1","name":"1.Alles uit","x":110,"y":240,"wires":[["5cea949e.29749c"]]},{"id":"34dc81af.33f8ce","type":"nora-switch","z":"58ffe4aa.948ebc","devicename":"Mood Lights","roomhint":"Living Room","name":"","passthru":false,"nora":"cd4ef92c.02f5a8","topic":"","onvalue":"true","onvalueType":"str","offvalue":"false","offvalueType":"str","x":110,"y":120,"wires":[["cab618db.40b118"]]},{"id":"cab618db.40b118","type":"switch","z":"58ffe4aa.948ebc","name":"","property":"payload","propertyType":"msg","rules":[{"t":"eq","v":"true","vt":"str"},{"t":"eq","v":"false","vt":"str"}],"checkall":"true","repair":false,"outputs":2,"x":290,"y":120,"wires":[["513a5fef.e19ad"],["6a2a9e35.5153b"]]},{"id":"87ee20f3.819ee","type":"velbus-switch","z":"58ffe4aa.948ebc","address":"49","channel":"4","name":"Sfeer","x":610,"y":80,"wires":[[]]},{"id":"214d46d9.0963aa","type":"velbus-switch","z":"58ffe4aa.948ebc","address":"17","channel":"1","name":"Alles uit","x":620,"y":140,"wires":[[]]},{"id":"513a5fef.e19ad","type":"change","z":"58ffe4aa.948ebc","name":"press","rules":[{"t":"set","p":"payload","pt":"msg","to":"press","tot":"str"}],"action":"","property":"","from":"","to":"","reg":false,"x":470,"y":80,"wires":[["87ee20f3.819ee"]]},{"id":"6a2a9e35.5153b","type":"change","z":"58ffe4aa.948ebc","name":"press","rules":[{"t":"set","p":"payload","pt":"msg","to":"press","tot":"str"}],"action":"","property":"","from":"","to":"","reg":false,"x":470,"y":140,"wires":[["214d46d9.0963aa"]]},{"id":"99a4866.0b8e078","type":"function","z":"8b6efa11.bcdc48","name":"get","func":"var lightOn = global.get(\"DiningLight\");\n\nif (msg.payload === \"pressed\") {\n    msg.payload = {on:!lightOn, transitionTimeint: 3}\n} \n\n\nreturn msg;","outputs":1,"noerr":0,"x":350,"y":140,"wires":[["f995b927.3cb4b8"]]},{"id":"d75ea76a.052318","type":"velbus-switch","z":"8b6efa11.bcdc48","address":"17","channel":"2","name":"Tafel @deur","x":190,"y":100,"wires":[["99a4866.0b8e078"]]},{"id":"893c16b0.67f1c8","type":"hue-group","z":"8b6efa11.bcdc48","name":"Bas Bed Room","bridge":"cac76e2e.508a7","groupid":"5","colornamer":true,"x":440,"y":340,"wires":[[]]},{"id":"f0d77f5d.7aeb9","type":"velbus-switch","z":"8b6efa11.bcdc48","address":"17","channel":"1","name":"Alles uit Deur","x":110,"y":320,"wires":[["5cea949e.29749c"]]},{"id":"cf7e036d.5b2ea","type":"change","z":"16a99bc9.937dd4","name":"turn off","rules":[{"t":"set","p":"payload","pt":"msg","to":"0","tot":"num"}],"action":"","property":"","from":"","to":"","reg":false,"x":480,"y":220,"wires":[["89d2ff26.c1605"]]},{"id":"e83861af.39cc9","type":"velbus-switch","z":"16a99bc9.937dd4","address":"18","channel":"1","name":"1.Alles uit","x":100,"y":200,"wires":[["14ed936d.a25b0d"]]},{"id":"e0f9ff8f.9e23a","type":"velbus-switch","z":"16a99bc9.937dd4","address":"17","channel":"1","name":"Alles uit Deur","x":110,"y":240,"wires":[["14ed936d.a25b0d"]]},{"id":"8f8c370f.0bcea8","type":"velbus-switch","z":"16a99bc9.937dd4","address":"16","channel":"2","name":"Tafel","x":90,"y":320,"wires":[["5dc2dc66.108414"]]},{"id":"5dc2dc66.108414","type":"change","z":"16a99bc9.937dd4","name":"turn on","rules":[{"t":"set","p":"payload","pt":"msg","to":"1","tot":"num"}],"action":"","property":"","from":"","to":"","reg":false,"x":480,"y":280,"wires":[["89d2ff26.c1605"]]},{"id":"44bb012e.a64be","type":"velbus-switch","z":"16a99bc9.937dd4","address":"16","channel":"3","name":"Living","x":90,"y":360,"wires":[["5dc2dc66.108414"]]},{"id":"54b4289c.473ec8","type":"velbus-switch","z":"16a99bc9.937dd4","address":"16","channel":"4","name":"Sfeer","x":90,"y":400,"wires":[["5dc2dc66.108414"]]},{"id":"d60e378c.2c1e18","type":"velbus-switch","z":"16a99bc9.937dd4","address":"16","channel":"5","name":"TV Kast","x":100,"y":440,"wires":[["5dc2dc66.108414"]]},{"id":"8846a816.71a628","type":"velbus-switch","z":"16a99bc9.937dd4","address":"16","channel":"6","name":"Keuken","x":100,"y":480,"wires":[["5dc2dc66.108414"]]},{"id":"478b6234.4019ec","type":"velbus-switch","z":"16a99bc9.937dd4","address":"17","channel":"2","name":"Tafel","x":290,"y":420,"wires":[["4e635104.0f965"]]},{"id":"4e635104.0f965","type":"change","z":"16a99bc9.937dd4","name":"turn on","rules":[{"t":"set","p":"payload","pt":"msg","to":"1","tot":"num"}],"action":"","property":"","from":"","to":"","reg":false,"x":480,"y":340,"wires":[["89d2ff26.c1605"]]},{"id":"264c0660.22170a","type":"velbus-switch","z":"16a99bc9.937dd4","address":"17","channel":"3","name":"Living","x":290,"y":460,"wires":[["4e635104.0f965"]]},{"id":"47247e5e.cf15b","type":"velbus-switch","z":"16a99bc9.937dd4","address":"17","channel":"4","name":"Sfeer","x":290,"y":500,"wires":[["4e635104.0f965"]]},{"id":"aaa02d8.79eadd","type":"velbus-switch","z":"16a99bc9.937dd4","address":"17","channel":"6","name":"Keuken","x":300,"y":540,"wires":[["4e635104.0f965"]]},{"id":"73d6de7d.3d318","type":"velbus-switch","z":"16a99bc9.937dd4","address":"17","channel":"7","name":"TV Kast","x":300,"y":580,"wires":[["4e635104.0f965"]]},{"id":"8da3f7ea.308bc8","type":"velbus-switch","z":"16a99bc9.937dd4","address":"17","channel":"8","name":"PC","x":290,"y":620,"wires":[["4e635104.0f965"]]},{"id":"b74e5892.becdd8","type":"velbus-switch","z":"16a99bc9.937dd4","address":"18","channel":"2","name":"2. Tafel","x":500,"y":440,"wires":[["44a768fd.510e48"]]},{"id":"44a768fd.510e48","type":"change","z":"16a99bc9.937dd4","name":"turn on","rules":[{"t":"set","p":"payload","pt":"msg","to":"1","tot":"num"}],"action":"","property":"","from":"","to":"","reg":false,"x":660,"y":500,"wires":[["89d2ff26.c1605"]]},{"id":"bb36d525.f11688","type":"velbus-switch","z":"16a99bc9.937dd4","address":"18","channel":"3","name":"Alles aan","x":500,"y":480,"wires":[["44a768fd.510e48"]]},{"id":"3f8dc077.0b52","type":"velbus-switch","z":"16a99bc9.937dd4","address":"18","channel":"4","name":"???","x":490,"y":520,"wires":[["44a768fd.510e48"]]},{"id":"9d3ba633.64a6b8","type":"velbus-switch","z":"16a99bc9.937dd4","address":"18","channel":"5","name":"3. Sfeer","x":500,"y":560,"wires":[["44a768fd.510e48"]]},{"id":"14ed936d.a25b0d","type":"switch","z":"16a99bc9.937dd4","name":"Long press","property":"payload","propertyType":"msg","rules":[{"t":"eq","v":"longPressed","vt":"str"}],"checkall":"true","repair":false,"outputs":1,"x":290,"y":220,"wires":[["cf7e036d.5b2ea"]],"outputLabels":["long pressed"]},{"id":"e2e63ad6.7db088","type":"nora-outlet","z":"58ffe4aa.948ebc","devicename":"Media Outlet","roomhint":"","name":"","passthru":false,"nora":"cd4ef92c.02f5a8","topic":"","onvalue":"1","onvalueType":"num","offvalue":"2","offvalueType":"num","x":120,"y":280,"wires":[["71725b0f.81a0b4"]]},{"id":"71725b0f.81a0b4","type":"mqtt out","z":"58ffe4aa.948ebc","name":"TV Kast","topic":"/sonoff1/relay/0/set","qos":"","retain":"","broker":"6fb1e1d1.68362","x":620,"y":280,"wires":[]},{"id":"c517f678.bd4f98","type":"inject","z":"8b6efa11.bcdc48","name":"","topic":"","payload":"","payloadType":"date","repeat":"","crontab":"","once":false,"onceDelay":0.1,"x":180,"y":60,"wires":[["462bcc16.ebd214"]]},{"id":"462bcc16.ebd214","type":"sun-position","z":"8b6efa11.bcdc48","name":"","positionConfig":"88bb4f42.b7938","rules":[],"onlyOnChange":"true","topic":"","outputs":1,"start":"","startType":"none","startOffset":0,"startOffsetType":"none","startOffsetMultiplier":60000,"end":"","endType":"none","endOffset":0,"endOffsetType":"none","endOffsetMultiplier":60000,"x":350,"y":60,"wires":[["ef4f71c.8224f9"]]},{"id":"ef4f71c.8224f9","type":"debug","z":"8b6efa11.bcdc48","name":"","active":false,"tosidebar":true,"console":false,"tostatus":false,"complete":"payload","x":530,"y":40,"wires":[]},{"id":"be2fabee.233968","type":"velbus-raw-bytes","z":"8b6efa11.bcdc48","name":"Clock update","bytes":"0x0F 0xFB 00 0x04 0xD8 {{day}} {{hour}} {{minute}} 0 0x04","x":580,"y":460,"wires":[]},{"id":"e072a4a1.72cd78","type":"inject","z":"8b6efa11.bcdc48","name":"Each day @12:00","topic":"","payload":"","payloadType":"date","repeat":"","crontab":"00 12 * * *","once":false,"onceDelay":0.1,"x":150,"y":440,"wires":[["322e36d9.b3feca"]]},{"id":"322e36d9.b3feca","type":"function","z":"8b6efa11.bcdc48","name":"inject Date","func":"let d = new Date();\nlet day = d.getDay()-1;\nif (day === -1) day = 0;\n\nlet payload = {day: 5, hour: d.getHours(), minute: d.getMinutes()}\nmsg.payload = payload;\nreturn msg;","outputs":1,"noerr":0,"x":370,"y":460,"wires":[[]]},{"id":"31e39dc8.4ce992","type":"inject","z":"8b6efa11.bcdc48","name":"@Launch","topic":"","payload":"","payloadType":"date","repeat":"","crontab":"","once":true,"onceDelay":"30","x":120,"y":480,"wires":[["322e36d9.b3feca"]]},{"id":"cfdd41f.53fffc","type":"velbus-switch","z":"8b6efa11.bcdc48","address":"23","channel":"9","name":"alarm light boven","x":810,"y":560,"wires":[[]]},{"id":"4c94e0e3.c8da8","type":"velbus-switch","z":"8b6efa11.bcdc48","address":"17","channel":"11","name":"cancel alarm boven","x":810,"y":600,"wires":[[]]},{"id":"d6c8f72d.6cfee8","type":"hue-light","z":"8b6efa11.bcdc48","name":"Bed room Bas","bridge":"cac76e2e.508a7","lightid":"12","colornamer":true,"x":280,"y":580,"wires":[["4319cd1d.3fd964"]]},{"id":"1b902504.7d6f7b","type":"velbus-switch","z":"8b6efa11.bcdc48","address":"49","channel":"2","name":"Tafel @TV","x":200,"y":180,"wires":[["99a4866.0b8e078"]]},{"id":"4319cd1d.3fd964","type":"switch","z":"8b6efa11.bcdc48","name":"","property":"payload.on","propertyType":"msg","rules":[{"t":"true"},{"t":"false"}],"checkall":"true","repair":false,"outputs":2,"x":470,"y":580,"wires":[["ec4ee969.a20b58"],["22eb031c.55f6ec"]]},{"id":"ec4ee969.a20b58","type":"change","z":"8b6efa11.bcdc48","name":"Press","rules":[{"t":"set","p":"payload","pt":"msg","to":"press","tot":"str"}],"action":"","property":"","from":"","to":"","reg":false,"x":630,"y":560,"wires":[["cfdd41f.53fffc"]]},{"id":"22eb031c.55f6ec","type":"change","z":"8b6efa11.bcdc48","name":"Press","rules":[{"t":"set","p":"payload","pt":"msg","to":"press","tot":"str"}],"action":"","property":"","from":"","to":"","reg":false,"x":630,"y":600,"wires":[["4c94e0e3.c8da8"]]},{"id":"943dbab5.9c3178","type":"velbus-switch","z":"8b6efa11.bcdc48","address":"18","channel":"8","name":"Kamer Bas","x":90,"y":520,"wires":[["813ad178.29c0a"]]},{"id":"dafeead8.751188","type":"inject","z":"8b6efa11.bcdc48","name":"","topic":"","payload":"true","payloadType":"bool","repeat":"","crontab":"","once":false,"onceDelay":0.1,"x":90,"y":580,"wires":[["d6c8f72d.6cfee8"]]},{"id":"e0115b5d.c44768","type":"inject","z":"8b6efa11.bcdc48","name":"","topic":"","payload":"false","payloadType":"bool","repeat":"","crontab":"","once":false,"onceDelay":0.1,"x":90,"y":620,"wires":[["d6c8f72d.6cfee8"]]},{"id":"813ad178.29c0a","type":"change","z":"8b6efa11.bcdc48","name":"","rules":[{"t":"set","p":"payload","pt":"msg","to":"false","tot":"bool"}],"action":"","property":"","from":"","to":"","reg":false,"x":280,"y":520,"wires":[["d6c8f72d.6cfee8"]]},{"id":"2712d68d.4bc54a","type":"inject","z":"90d7900f.39219","name":"","topic":"","payload":"","payloadType":"date","repeat":"5","crontab":"","once":false,"onceDelay":"","x":110,"y":80,"wires":[["ac192614.b6ccb8"]]},{"id":"ac192614.b6ccb8","type":"http request","z":"90d7900f.39219","name":"Assistant Timers","method":"GET","ret":"obj","url":"http://192.168.0.101:8008/setup/assistant/alarms","tls":"","x":280,"y":80,"wires":[["b2d8cff.b376f3"]]},{"id":"d86bc2a6.e8836","type":"debug","z":"90d7900f.39219","name":"","active":true,"tosidebar":true,"console":false,"tostatus":false,"complete":"payload","x":610,"y":60,"wires":[]},{"id":"b2d8cff.b376f3","type":"function","z":"90d7900f.39219","name":"Memo Text","func":"\nif (msg.payload.timer.length > 0) {\n    msg.payload.times = [];\n    msg.payload.timer.forEach((timer => {\n        \n        const now = new Date().getTime();\n        let msLeft;\n        let status;\n        if (timer.status === 1) { //running\n            status = \"running\";\n            msLeft =  timer.fire_time - now;\n            msLeft = Math.max(0, msLeft);\n        } else if (timer.status === 0) { //pause\n            status = \"paused\";\n            msLeft= timer.remaining_duration;\n        } else {\n            status = \"triggered\";\n            msLeft =  O;\n        }\n        let formattedTime = new Date(msLeft).toISOString()\n        formattedTime = formattedTime.substr(15,4)\n        \n        msg.payload.times.push({timeLeft: formattedTime, status: status})\n        msg.payload.nrOfDataBytes = 8;\n        let bytes = stringToDataBytes(formattedTime);\n        msg.payload.dataBytes = \"0xAC 0xFF 0 \" + bytes + \" 0\";\n    }));\n}\nif (!msg.payload.times) {\n    msg.payload.nrOfDataBytes = 8;\n    msg.payload.dataBytes = \"0xAC 0xFF 0 0 0 0 0 0\";\n} else {\n    \n}\nreturn msg\n\n\n\nfunction stringToDataBytes(s) {\n    let r = [];\n    for (let i=0; i<s.length; i++) {\n        r.push(s.charCodeAt(i))\n    }\n    return r.join(\" \");\n}","outputs":1,"noerr":0,"x":450,"y":80,"wires":[["d86bc2a6.e8836","3d168ddd.643db2"]]},{"id":"3d168ddd.643db2","type":"velbus-raw-bytes","z":"90d7900f.39219","name":"Memo Text","bytes":"0x0F 0xFB 0x11 {{nrOfDataBytes}} {{dataBytes}} FF 0x04","x":610,"y":100,"wires":[]},{"id":"92c84d3d.68579","type":"inject","z":"58ffe4aa.948ebc","name":"Sfeer aan","topic":"","payload":"press","payloadType":"str","repeat":"","crontab":"","once":false,"onceDelay":0.1,"x":460,"y":20,"wires":[["87ee20f3.819ee"]]},{"id":"c8164405.cf5408","type":"mqtt out","z":"16a99bc9.937dd4","name":"Badkamer","topic":"shellies/shelly1-E0A148/relay/0/command","qos":"","retain":"","broker":"6fb1e1d1.68362","x":770,"y":760,"wires":[]},{"id":"55243116.65c44","type":"inject","z":"16a99bc9.937dd4","name":"","topic":"","payload":"on","payloadType":"str","repeat":"","crontab":"","once":false,"onceDelay":0.1,"x":530,"y":780,"wires":[["c8164405.cf5408"]]},{"id":"7941d65f.94fc78","type":"inject","z":"16a99bc9.937dd4","name":"","topic":"","payload":"off","payloadType":"str","repeat":"","crontab":"","once":false,"onceDelay":0.1,"x":530,"y":820,"wires":[["c8164405.cf5408"]]},{"id":"f6a31a0c.ec6ce8","type":"inject","z":"8b6efa11.bcdc48","name":"On","topic":"","payload":"true","payloadType":"bool","repeat":"","crontab":"","once":false,"onceDelay":0.1,"x":470,"y":540,"wires":[["ec4ee969.a20b58"]]},{"id":"12dacd.e072d533","type":"inject","z":"8b6efa11.bcdc48","name":"Off","topic":"","payload":"true","payloadType":"bool","repeat":"","crontab":"","once":false,"onceDelay":0.1,"x":470,"y":620,"wires":[["22eb031c.55f6ec"]]},{"id":"de949e33.ca80b","type":"inject","z":"8b6efa11.bcdc48","name":"","topic":"","payload":"true","payloadType":"bool","repeat":"","crontab":"","once":false,"onceDelay":0.1,"x":370,"y":100,"wires":[["f995b927.3cb4b8"]]},{"id":"94d7c925.c370a8","type":"inject","z":"8b6efa11.bcdc48","name":"","topic":"","payload":"false","payloadType":"bool","repeat":"","crontab":"","once":false,"onceDelay":0.1,"x":350,"y":180,"wires":[["f995b927.3cb4b8"]]}]